LICENSE
MANIFEST.in
readme.md
setup.py
chainsoup/__init__.py
chainsoup/args.py
chainsoup/base.py
chainsoup/exceptions.py
chainsoup/pipeline.py
chainsoup/types.py
chainsoup.egg-info/PKG-INFO
chainsoup.egg-info/SOURCES.txt
chainsoup.egg-info/dependency_links.txt
chainsoup.egg-info/requires.txt
chainsoup.egg-info/top_level.txt