Metadata-Version: 2.1
Name: chainsoup
Version: 0.1.8
Summary: A fluent, pipeline-based interface for querying HTML/XML with BeautifulSoup.
Home-page: https://github.com/thefcraft/chainsoup
Author: ThefCraft
Author-email: sisodiyalaksh@gmail.com
License: UNKNOWN
Keywords: beautifulsoup,bs4,scraping,parser,html,xml,fluent,chainable,pipeline
Platform: UNKNOWN
Classifier: Development Status :: 4 - Beta
Classifier: Intended Audience :: Developers
Classifier: Topic :: Software Development :: Libraries :: Python Modules
Classifier: Topic :: Text Processing :: Markup :: HTML
Classifier: Topic :: Text Processing :: Markup :: XML
Classifier: License :: OSI Approved :: MIT License
Classifier: Operating System :: OS Independent
Classifier: Programming Language :: Python :: 3
Classifier: Programming Language :: Python :: 3.8
Classifier: Programming Language :: Python :: 3.9
Classifier: Programming Language :: Python :: 3.10
Classifier: Programming Language :: Python :: 3.11
Classifier: Programming Language :: Python :: 3.12
Requires-Python: >=3.8
License-File: LICENSE
